CONSTANTS.py
filament_augmentation/__init__.py
filament_augmentation/augment/__init__.py
filament_augmentation/augment/_augmentation.py
filament_augmentation/augment/augment_error.py
filament_augmentation/generator/__init__.py
filament_augmentation/generator/_filament_generator.py
filament_augmentation/generator/filament_dataset.py
filament_augmentation/loader/__init__.py
filament_augmentation/loader/filament_dataloader.py
filament_augmentation/metadata/__init__.py
filament_augmentation/metadata/filament_metadata.py
filament_augmentation/transforms/__init__.py
filament_augmentation/transforms/_transformation.py
filament_augmentation/transforms/projections.py
filament_augmentation/utils/__init__.py
filament_augmentation/utils/file_utilities.py
filament_augmentation/utils/image_utils.py
filament_augmentation/utils/timestamp_utilites.py
filament_augmentation_engine-0.0.3.data/data/petdata/2015_chir_data2.json
filament_augmentation_engine-0.0.3.data/data/petdata/sample/2015/08/01/bbso_halph_fl_20150801_174814.jpg
filament_augmentation_engine-0.0.3.data/data/petdata/sample/2015/08/01/bbso_halph_fl_20150801_203114.jpg
filament_augmentation_engine-0.0.3.data/data/petdata/sample/2015/08/01/bbso_halph_fr_20150801_174814.jpg
filament_augmentation_engine-0.0.3.data/data/petdata/sample/2015/08/01/bbso_halph_fr_20150801_203114.jpg
filament_augmentation_engine-0.0.3.data/data/petdata/sample/2015/08/01/gong_06768_fd_20150801_002203.jpg
filament_augmentation_engine-0.0.3.data/data/petdata/sample/2015/08/01/gong_06768_fd_20150801_012203.jpg
filament_augmentation_engine-0.0.3.data/data/petdata/sample/2015/08/01/gong_06768_fd_20150801_142103.jpg
filament_augmentation_engine-0.0.3.data/data/petdata/sample/2015/08/01/gong_06768_fd_20150801_152103.jpg
filament_augmentation_engine-0.0.3.data/data/petdata/sample/2015/08/01/gong_06768_fd_20150801_162103.jpg
filament_augmentation_engine-0.0.3.data/data/petdata/sample/2015/08/01/gong_06768_fd_20150801_172103.jpg
filament_augmentation_engine-0.0.3.dist-info/LICENSE
filament_augmentation_engine-0.0.3.dist-info/METADATA
filament_augmentation_engine-0.0.3.dist-info/WHEEL
filament_augmentation_engine-0.0.3.dist-info/top_level.txt
filament_augmentation_engine-0.0.3.dist-info/RECORD
