Metadata-Version: 2.1
Name: filament-augmentation-engine
Version: 0.0.3
Summary: Solar Filaments data augmentation demo package
Home-page: https://github.com/Shreejaa/augmentation_engine
Author: Shreejaa Talla
Author-email: stalla1@student.gsu.edu
License: UNKNOWN
Project-URL: Source, https://github.com/Shreejaa/augmentation_engine
Platform: UNKNOWN
Classifier: Programming Language :: Python :: 3
Classifier: Operating System :: OS Independent
Classifier: License :: OSI Approved :: MIT License
License-File: LICENSE
Requires-Dist: sortedcontainers
Requires-Dist: opencv-python
Requires-Dist: torchvision
Requires-Dist: pillow
Requires-Dist: pycocotools
